jsontableschema_bigquery/VERSION
jsontableschema_bigquery/__init__.py
jsontableschema_bigquery/mappers.py
jsontableschema_bigquery/storage.py
jsontableschema_bigquery-0.5.0.dist-info/DESCRIPTION.rst
jsontableschema_bigquery-0.5.0.dist-info/METADATA
jsontableschema_bigquery-0.5.0.dist-info/RECORD
jsontableschema_bigquery-0.5.0.dist-info/WHEEL
jsontableschema_bigquery-0.5.0.dist-info/metadata.json
jsontableschema_bigquery-0.5.0.dist-info/top_level.txt
